<?xml version="1.0" encoding="UTF-8"?>
<conversion>
  <applied-converters>
    <converter id="android-module-to-java-module" />
    <converter id="android-native-run-configurations" />
    <converter id="android-proguard-options" />
    <converter id="android-sdk-library" />
    <converter id="groovy-modules-to-facets" />
    <converter id="groovy-script-run-configurations" />
    <converter id="junit-to-android-junit-configurations" />
    <converter id="remove-java-aware-configurations" />
  </applied-converters>
  <project-files>
    <file path="C:\Users\Vincent\AndroidStudioProjects\Messenger\.idea\compiler.xml" timestamp="1500814754708" />
    <file path="C:\Users\Vincent\AndroidStudioProjects\Messenger\.idea\copyright\profiles_settings.xml" timestamp="1500814754716" />
    <file path="C:\Users\Vincent\AndroidStudioProjects\Messenger\.idea\gradle.xml" timestamp="1500814762659" />
    <file path="C:\Users\Vincent\AndroidStudioProjects\Messenger\.idea\libraries\animated_vector_drawable_26_0_0_alpha1.xml" timestamp="1500814770043" />
    <file path="C:\Users\Vincent\AndroidStudioProjects\Messenger\.idea\libraries\appcompat_v7_26_0_0_alpha1.xml" timestamp="1500814770064" />
    <file path="C:\Users\Vincent\AndroidStudioProjects\Messenger\.idea\libraries\constraint_layout_1_0_2.xml" timestamp="1500814770074" />
    <file path="C:\Users\Vincent\AndroidStudioProjects\Messenger\.idea\libraries\constraint_layout_solver_1_0_2.xml" timestamp="1500814770091" />
    <file path="C:\Users\Vincent\AndroidStudioProjects\Messenger\.idea\libraries\espresso_core_2_2_2.xml" timestamp="1500814770104" />
    <file path="C:\Users\Vincent\AndroidStudioProjects\Messenger\.idea\libraries\espresso_idling_resource_2_2_2.xml" timestamp="1500814770116" />
    <file path="C:\Users\Vincent\AndroidStudioProjects\Messenger\.idea\libraries\exposed_instrumentation_api_publish_0_5.xml" timestamp="1500814770122" />
    <file path="C:\Users\Vincent\AndroidStudioProjects\Messenger\.idea\libraries\hamcrest_core_1_3.xml" timestamp="1500814770130" />
    <file path="C:\Users\Vincent\AndroidStudioProjects\Messenger\.idea\libraries\hamcrest_integration_1_3.xml" timestamp="1500814770153" />
    <file path="C:\Users\Vincent\AndroidStudioProjects\Messenger\.idea\libraries\hamcrest_library_1_3.xml" timestamp="1500814770165" />
    <file path="C:\Users\Vincent\AndroidStudioProjects\Messenger\.idea\libraries\javawriter_2_1_1.xml" timestamp="1500814770173" />
    <file path="C:\Users\Vincent\AndroidStudioProjects\Messenger\.idea\libraries\javax_annotation_api_1_2.xml" timestamp="1500814770180" />
    <file path="C:\Users\Vincent\AndroidStudioProjects\Messenger\.idea\libraries\javax_inject_1.xml" timestamp="1500814770331" />
    <file path="C:\Users\Vincent\AndroidStudioProjects\Messenger\.idea\libraries\jsr305_2_0_1.xml" timestamp="1500814770339" />
    <file path="C:\Users\Vincent\AndroidStudioProjects\Messenger\.idea\libraries\junit_4_12.xml" timestamp="1500814770696" />
    <file path="C:\Users\Vincent\AndroidStudioProjects\Messenger\.idea\libraries\rules_0_5.xml" timestamp="1500814770960" />
    <file path="C:\Users\Vincent\AndroidStudioProjects\Messenger\.idea\libraries\runner_0_5.xml" timestamp="1500814770978" />
    <file path="C:\Users\Vincent\AndroidStudioProjects\Messenger\.idea\libraries\support_annotations_26_0_0_alpha1.xml" timestamp="1500814771002" />
    <file path="C:\Users\Vincent\AndroidStudioProjects\Messenger\.idea\libraries\support_compat_26_0_0_alpha1.xml" timestamp="1500814771014" />
    <file path="C:\Users\Vincent\AndroidStudioProjects\Messenger\.idea\libraries\support_core_ui_26_0_0_alpha1.xml" timestamp="1500814771026" />
    <file path="C:\Users\Vincent\AndroidStudioProjects\Messenger\.idea\libraries\support_core_utils_26_0_0_alpha1.xml" timestamp="1500814771033" />
    <file path="C:\Users\Vincent\AndroidStudioProjects\Messenger\.idea\libraries\support_fragment_26_0_0_alpha1.xml" timestamp="1500814771042" />
    <file path="C:\Users\Vincent\AndroidStudioProjects\Messenger\.idea\libraries\support_media_compat_26_0_0_alpha1.xml" timestamp="1500814771056" />
    <file path="C:\Users\Vincent\AndroidStudioProjects\Messenger\.idea\libraries\support_v4_26_0_0_alpha1.xml" timestamp="1500814771117" />
    <file path="C:\Users\Vincent\AndroidStudioProjects\Messenger\.idea\libraries\support_vector_drawable_26_0_0_alpha1.xml" timestamp="1500814771131" />
    <file path="C:\Users\Vincent\AndroidStudioProjects\Messenger\.idea\misc.xml" timestamp="1501248169422" />
    <file path="C:\Users\Vincent\AndroidStudioProjects\Messenger\.idea\modules.xml" timestamp="1500814769975" />
    <file path="C:\Users\Vincent\AndroidStudioProjects\Messenger\.idea\runConfigurations.xml" timestamp="1500814770006" />
    <file path="C:\Users\Vincent\AndroidStudioProjects\Messenger\.idea\workspace.xml" timestamp="1501248036401" />
    <file path="C:\Users\Vincent\AndroidStudioProjects\Messenger\Messenger.iml" timestamp="1500814769849" />
    <file path="C:\Users\Vincent\AndroidStudioProjects\Messenger\app\app.iml" timestamp="1500820784952" />
  </project-files>
</conversion>

